Metadata-Version: 2.4
Name: genmod
Version: 3.10.2
Summary: Annotate genetic inheritance models in Variant Call Format (VCF) files
Project-URL: Repository, http://github.com/Clinical-Genomics/genmod
Project-URL: Changelog, https://github.com/Clinical-Genomics/genmod/blob/main/CHANGELOG.md
Project-URL: Bug Tracker, https://github.com/Clinical-Genomics/genmod/issues
Author-email: Mans Magnuson <mans.magnusson@scilifelab.se>, Tor Björgen <tor.bjorgen@scilifelab.se>, Felix Lenner <felix.lenner@scilifelab.se>, Anders Jemt <anders.jemt@scilifelab.se>, Daniel Nilsson <daniel.nilsson@ki.se>
License: MIT License
License-File: LICENSE.txt
Keywords: inheritance,variants,vcf
Classifier: Development Status :: 5 - Production/Stable
Classifier: Intended Audience :: Science/Research
Classifier: License :: OSI Approved :: MIT License
Classifier: Operating System :: MacOS :: MacOS X
Classifier: Operating System :: Unix
Classifier: Programming Language :: Python
Classifier: Programming Language :: Python :: 3
Classifier: Programming Language :: Python :: Implementation :: CPython
Classifier: Topic :: Scientific/Engineering :: Bio-Informatics
Classifier: Topic :: Scientific/Engineering :: Medical Science Apps.
Requires-Python: >=3.7
Requires-Dist: click
Requires-Dist: configobj
Requires-Dist: extract-vcf
Requires-Dist: importlib-resources
Requires-Dist: interval-tree>=0.3.4
Requires-Dist: intervaltree>=3.1.0
Requires-Dist: ped-parser
Requires-Dist: pytabix
Requires-Dist: six
